.coveragerc
.gitattributes
.travis.yml
AUTHORS
COPYING
ChangeLog
Dockerfile
MANIFEST.in
Makefile
README.rst
doc-requirements.txt
requirements.txt
setup.cfg
setup.py
test-requirements.txt
tox.ini
contrib/jquery-1.9.1.js
contrib/jquery.tablefilter.js
contrib/jquery.tablesorter.js
contrib/jsi18n.js
contrib/update-servermon.sh
contrib/bootstrap/css/bootstrap-responsive.css
contrib/bootstrap/css/bootstrap.css
contrib/bootstrap/js/bootstrap.js
contrib/flot/API.md
contrib/flot/CONTRIBUTING.md
contrib/flot/FAQ.md
contrib/flot/LICENSE.txt
contrib/flot/Makefile
contrib/flot/NEWS.md
contrib/flot/PLUGINS.md
contrib/flot/README.md
contrib/flot/build.log
contrib/flot/excanvas.js
contrib/flot/jquery.colorhelpers.js
contrib/flot/jquery.flot.canvas.js
contrib/flot/jquery.flot.categories.js
contrib/flot/jquery.flot.crosshair.js
contrib/flot/jquery.flot.errorbars.js
contrib/flot/jquery.flot.fillbetween.js
contrib/flot/jquery.flot.image.js
contrib/flot/jquery.flot.js
contrib/flot/jquery.flot.navigate.js
contrib/flot/jquery.flot.pie.js
contrib/flot/jquery.flot.resize.js
contrib/flot/jquery.flot.selection.js
contrib/flot/jquery.flot.stack.js
contrib/flot/jquery.flot.symbol.js
contrib/flot/jquery.flot.threshold.js
contrib/flot/jquery.flot.time.js
contrib/flot/jquery.js
doc/conf.py
doc/design-0.3.rst
doc/design-0.4.rst
doc/design-0.5.rst
doc/design-0.6.rst
doc/design-0.7.rst
doc/epydoc.conf
doc/glossary.rst
doc/index.rst
doc/install.rst
doc/upgrade.rst
gunicorn/servermon.conf
servermon/__init__.py
servermon/apt2xml.py
servermon/compat.py
servermon/manage.py
servermon/settings.py
servermon/settings.py.dist
servermon/settings_test.py
servermon/settings_test_mysql.py
servermon/settings_test_postgres.py
servermon/settings_test_sqlite.py
servermon/urls.py
servermon/wsgi.py
servermon.egg-info/PKG-INFO
servermon.egg-info/SOURCES.txt
servermon.egg-info/dependency_links.txt
servermon.egg-info/not-zip-safe
servermon.egg-info/pbr.json
servermon.egg-info/requires.txt
servermon.egg-info/top_level.txt
servermon/djangobackends/StripWhitespaceMiddleware.py
servermon/djangobackends/__init__.py
servermon/djangobackends/context_processors.py
servermon/djangobackends/ldapBackend.py
servermon/hwdoc/__init__.py
