Metadata-Version: 1.1
Name: servermon
Version: 0.7.0
Summary: An inventory project to facilitate server monitoring and management through Puppet.
Home-page: https://github.com/servermon/servermon
Author: Alexandros Kosiaris
Author-email: akosiaris@gmail.com
License: 'ISC'
Keywords: puppet
Platform: UNKNOWN
Classifier: Development Status :: 5 - Production/Stable
Classifier: Framework :: Django
Classifier: Intended Audience :: System Administrators
Classifier: License :: OSI Approved :: ISC License (ISCL)
Classifier: Natural Language :: English
Classifier: Programming Language :: Python
Classifier: Topic :: System :: Clustering
Classifier: Topic :: System :: Systems Administration
Classifier: Topic :: System :: Monitoring
